divinepy/__init__.py
divinepy/_nbdev.py
divinepy/core.py
divinepy/dem_corrections.py
divinepy/dems.py
divinepy/divdata.py
divinepy/hpar.py
divinepy/l2data.py
divinepy/l3data.py
divinepy-0.1.1.dist-info/LICENSE
divinepy-0.1.1.dist-info/METADATA
divinepy-0.1.1.dist-info/WHEEL
divinepy-0.1.1.dist-info/entry_points.txt
divinepy-0.1.1.dist-info/top_level.txt
divinepy-0.1.1.dist-info/RECORD
