Metadata-Version: 2.1
Name: divinepy
Version: 0.1.1
Summary: Diviner data tools
Home-page: https://github.com/michaelaye/divinepy/tree/master/
Author: Michael Aye
Author-email: kmichael.aye@gmail.com
License: Apache Software License 2.0
Keywords: Moon,Data
Platform: UNKNOWN
Classifier: Development Status :: 3 - Alpha
Classifier: Intended Audience :: Developers
Classifier: License :: OSI Approved :: Apache Software License
Classifier: Natural Language :: English
Classifier: Programming Language :: Python :: 3.7
Classifier: Programming Language :: Python :: 3.8
Requires-Python: >=3.7
Requires-Dist: pandas
Requires-Dist: xarray
Requires-Dist: rasterio
